mf88_affilitest/__init__.py
mf88_affilitest/api.py
mf88_affilitest/devices.py
mf88_affilitest/endpoints.py
mf88_affilitest-0.1.6.dist-info/WHEEL
mf88_affilitest-0.1.6.dist-info/METADATA
mf88_affilitest-0.1.6.dist-info/RECORD
