Metadata-Version: 2.1
Name: mf88-affilitest
Version: 0.1.6
Summary: 
Author: vutr
Author-email: me@vutr.io
Requires-Python: >=3.7.5,<4.0.0
Classifier: Programming Language :: Python :: 3
Classifier: Programming Language :: Python :: 3.8
Requires-Dist: requests (>=2.24.0,<3.0.0)
